flask_keycloak/__init__.py
flask_keycloak/constants.py
flask_keycloak/extension.py
flask_keycloak/log.py
flask_keycloak/middlewares.py
flask_keycloak/routes.py
flask_keycloak/utils.py
flask_keycloak-1.1.0.dist-info/METADATA
flask_keycloak-1.1.0.dist-info/RECORD
flask_keycloak-1.1.0.dist-info/WHEEL
flask_keycloak-1.1.0.dist-info/top_level.txt
