Metadata-Version: 2.1
Name: flask-keycloak
Version: 1.1.0
Summary: flask integration with keycloak
Home-page: https://github.com/akhilputhiry/flask-keycloak
Author: Akhil Lawrence
Author-email: akhilputhiry@gmail.com
License: UNKNOWN
Platform: UNKNOWN
Classifier: Programming Language :: Python :: 3.6
Classifier: Framework :: Flask
Requires-Dist: keycloak (==1.6.0)
